istacpy/__init__.py
istacpy/config.py
istacpy/exceptions.py
istacpy/services.py
istacpy/indicators/__init__.py
istacpy/indicators/geographic.py
istacpy/indicators/indicators.py
istacpy/indicators/systems.py
istacpy/indicators/lite/__init__.py
istacpy/indicators/lite/i18n.py
istacpy/indicators/lite/indicators.py
istacpy/indicators/lite/services.py
istacpy/indicators/lite/dimensions/__init__.py
istacpy/indicators/lite/dimensions/base.py
istacpy/indicators/lite/dimensions/geographical.py
istacpy/indicators/lite/dimensions/measure.py
istacpy/indicators/lite/dimensions/time.py
istacpy/statisticalresources/__init__.py
istacpy/statisticalresources/cubes.py
istacpy/statisticalresources/queries.py
istacpy/structuralresources/__init__.py
istacpy/structuralresources/category.py
istacpy/structuralresources/classifications.py
istacpy/structuralresources/concepts.py
istacpy/structuralresources/datastructures.py
istacpy/structuralresources/variables.py
istacpy-0.8.1.dist-info/licenses/LICENSE
istacpy-0.8.1.dist-info/METADATA
istacpy-0.8.1.dist-info/WHEEL
istacpy-0.8.1.dist-info/top_level.txt
istacpy-0.8.1.dist-info/RECORD
