Metadata-Version: 2.4
Name: istacpy
Version: 0.8.1
Summary: Python package for obtaining open data from Instituto Canario de Estadística (ISTAC)
Home-page: https://www.gobiernodecanarias.org/istac/api/
Author: Instituto Canario de Estadistica (ISTAC)
Author-email: consultas.istac@gobiernodecanarias.org
License: gpl-3.0
Keywords: istacpy,ISTAC,Instituto Canario de Estadistica,API,JSON
Classifier: Development Status :: 4 - Beta
Classifier: Intended Audience :: Science/Research
Classifier: Intended Audience :: Developers
Classifier: Operating System :: OS Independent
Classifier: License :: OSI Approved :: GNU General Public License v3 (GPLv3)
Classifier: Programming Language :: Python
Classifier: Topic :: Scientific/Engineering :: Mathematics
Classifier: Topic :: Software Development :: Libraries
Classifier: Topic :: Internet :: WWW/HTTP
Requires-Python: >=3.6
License-File: LICENSE
Requires-Dist: requests
Requires-Dist: pandas
Dynamic: author
Dynamic: author-email
Dynamic: classifier
Dynamic: description
Dynamic: description-content-type
Dynamic: home-page
Dynamic: keywords
Dynamic: license
Dynamic: license-file
Dynamic: requires-dist
Dynamic: requires-python
Dynamic: summary
